MANIFEST.in
README.rst
setup.cfg
setup.py
conf/__init__.py
conf/ide.cfg
nagare/__init__.py
nagare.ide.egg-info/PKG-INFO
nagare.ide.egg-info/SOURCES.txt
nagare.ide.egg-info/dependency_links.txt
nagare.ide.egg-info/entry_points.txt
nagare.ide.egg-info/namespace_packages.txt
nagare.ide.egg-info/not-zip-safe
nagare.ide.egg-info/requires.txt
nagare.ide.egg-info/top_level.txt
nagare/ide/__init__.py
nagare/ide/admin.py
nagare/ide/app.py
nagare/ide/bespin_editor.py
nagare/ide/constants.py
nagare/ide/error.py
nagare/ide/log.py
nagare/ide/security.py
nagare/ide/tree.py
nagare/ide/workspace.py
static/__init__.py
static/ide.css
static/ide.js
static/images/cccccc.png
static/images/cross_off.png
static/images/cross_on.png
static/images/dadada.png
static/images/e6e6e6.png
static/images/error_bg.png
static/images/file_exception.png
static/images/file_unknown.png
static/images/icn_copy.png
static/images/icn_cut.png
static/images/icn_paste.png
static/images/icn_redo.png
static/images/icn_reload.png
static/images/icn_save.png
static/images/icn_undo.png
static/images/lm.gif
static/images/lmh.gif
static/images/ln.gif
static/images/loading.gif
static/images/lp.gif
static/images/lph.gif
static/images/tm.gif
static/images/tmh.gif
static/images/tn.gif
static/images/tp.gif
static/images/tph.gif
static/images/vline.gif
static/js/bespin/bespin.js
static/js/bespin/bootstrap_worker.js
static/js/bespin/command.js
static/js/bespin/events.js
static/js/bespin/client/filesystem.js
static/js/bespin/client/server.js
static/js/bespin/client/session.js
static/js/bespin/client/settings.js
static/js/bespin/editor/actions.js
static/js/bespin/editor/clipboard.js
static/js/bespin/editor/codecompletion.js
static/js/bespin/editor/component.js
static/js/bespin/editor/cursor.js
static/js/bespin/editor/dependencies.js
static/js/bespin/editor/editor.js
static/js/bespin/editor/embed.js
static/js/bespin/editor/events.js
static/js/bespin/editor/formatter.js
static/js/bespin/editor/history.js
static/js/bespin/editor/model.js
static/js/bespin/editor/toolbar.js
static/js/bespin/page/editor/init.js
static/js/bespin/parser/parser.js
static/js/bespin/plugins/loader.js
static/js/bespin/plugins/loaderTest.js
static/js/bespin/syntax/base.js
static/js/bespin/syntax/codemirror/_base.js
